desionterminal/__init__.py
desionterminal/desi.py
desionterminal-1.0.0.dist-info/LICENSE.txt
desionterminal-1.0.0.dist-info/METADATA
desionterminal-1.0.0.dist-info/WHEEL
desionterminal-1.0.0.dist-info/top_level.txt
desionterminal-1.0.0.dist-info/RECORD
