Metadata-Version: 2.1
Name: desionterminal
Version: 1.0.0
Summary: A simple Python package that prints the Desiderata on your terminal.
Home-page: https://thepowerpoint.co.ke/desionterminal/home
Author: John Gitahi
Author-email: gitahi109@hotmail.com
Project-URL: Bug Tracker, https://thepowerpoint.co.ke/desionterminal-pages/names
Project-URL: repository, https://thepowerpoint.co.ke/desionterminal/dcfvgbhnj
Classifier: Programming Language :: Python :: 3
Classifier: License :: OSI Approved :: MIT License
Classifier: Operating System :: OS Independent
Requires-Python: >=3.6
License-File: LICENSE.txt
